robolog/__init__.py
robolog/img/_idea_robolog.drawio.png
robolog/img/md01.png
robolog/robolog.py
robolog-0.4.0.dist-info/LICENSE
robolog-0.4.0.dist-info/METADATA
robolog-0.4.0.dist-info/WHEEL
robolog-0.4.0.dist-info/RECORD
