Metadata-Version: 2.1
Name: robolog
Version: 0.4.0
Summary: Personalized logger for RPA solutions
Home-page: https://github.com/roboforge-solutions/robolog
License: MIT
Author: Wojciech Jankiewicz
Author-email: jankiwojciech@outlook.com
Requires-Python: >=3.10,<4.0
Classifier: License :: OSI Approved :: MIT License
Classifier: Programming Language :: Python :: 3
Classifier: Programming Language :: Python :: 3.10
Classifier: Programming Language :: Python :: 3.11
Classifier: Programming Language :: Python :: 3.12
Requires-Dist: colorlog
